oarepo_ui/__init__.py
oarepo_ui/cli.py
oarepo_ui/config.py
oarepo_ui/ext.py
oarepo_ui/for_translations_only.py
oarepo_ui/proxies.py
oarepo_ui/utils.py
oarepo_ui/views.py
oarepo_ui/vite.py
oarepo_ui/webpack.py
oarepo_ui/css/builtin.css
oarepo_ui/resources/__init__.py
oarepo_ui/resources/config.py
oarepo_ui/resources/file_resource.py
oarepo_ui/resources/links.py
oarepo_ui/resources/resource.py
oarepo_ui/resources/signposting.py
oarepo_ui/resources/components/__init__.py
oarepo_ui/resources/components/access_empty_record.py
oarepo_ui/resources/components/babel.py
oarepo_ui/resources/components/base.py
oarepo_ui/resources/components/bleach.py
oarepo_ui/resources/components/communities.py
oarepo_ui/resources/components/custom_fields.py
oarepo_ui/resources/components/files.py
oarepo_ui/resources/components/files_locked.py
oarepo_ui/resources/components/permissions.py
oarepo_ui/resources/components/record_restriction.py
oarepo_ui/resources/templating/__init__.py
oarepo_ui/resources/templating/catalog.py
oarepo_ui/resources/templating/data.py
oarepo_ui/resources/templating/filters.py
oarepo_ui/services/__init__.py
oarepo_ui/services/custom_fields.py
oarepo_ui/static/images/identifiers/id.svg
oarepo_ui/static/images/identifiers/orcid.svg
oarepo_ui/static/images/identifiers/ror.svg
oarepo_ui/static/images/identifiers/scopus.svg
oarepo_ui/templates/components/AccessRight.jinja
oarepo_ui/templates/components/Array.jinja
oarepo_ui/templates/components/ClipboardCopyButton.jinja
oarepo_ui/templates/components/DefinitionLink.jinja
oarepo_ui/templates/components/EditForm.jinja
oarepo_ui/templates/components/Field.jinja
oarepo_ui/templates/components/IdentifierBadge.jinja
oarepo_ui/templates/components/IdentifiersAndLinks.jinja
oarepo_ui/templates/components/Metrics.jinja
oarepo_ui/templates/components/Multilingual.jinja
oarepo_ui/templates/components/PreviewSubheader.jinja
oarepo_ui/templates/components/RecordExport.jinja
oarepo_ui/templates/components/RecordSharing.jinja
oarepo_ui-6.0.0.dist-info/METADATA
oarepo_ui-6.0.0.dist-info/WHEEL
oarepo_ui-6.0.0.dist-info/entry_points.txt
oarepo_ui-6.0.0.dist-info/top_level.txt
oarepo_ui-6.0.0.dist-info/RECORD
