Metadata-Version: 2.4
Name: oarepo-ui
Version: 6.0.0
Summary: UI module for invenio 3.5+
Home-page: https://github.com/oarepo/oarepo-ui
Author: Mirek Simek
Author-email: miroslav.simek@vscht.cz
License: MIT
Keywords: oarepo ui
Platform: any
Classifier: Development Status :: 5 - Production/Stable
Requires-Python: >=3.10
Requires-Dist: importlib-metadata>=4.11.4
Requires-Dist: oarepo-runtime
Requires-Dist: jinja2-simple-tags
Requires-Dist: frozendict
Requires-Dist: jinjax==0.60
Provides-Extra: dev
Requires-Dist: oarepo-tools; extra == "dev"
Provides-Extra: workflows
Requires-Dist: oarepo-workflows; extra == "workflows"
Provides-Extra: tests
Requires-Dist: pytest-invenio; extra == "tests"
Requires-Dist: black; extra == "tests"
Requires-Dist: isort; extra == "tests"
Requires-Dist: autoflake; extra == "tests"
Requires-Dist: oarepo-workflows; extra == "tests"
